{
  "Type": 2,
  "JsonPlanets": [
    {
      "Name": "Gallinore",
      "ID": 429,
			"CoordX": 346.1,
      "CoordY": 55.3
    },
    {
      "Name": "Novi",
      "ID": 1430,
			"CoordX": 345.8,
      "CoordY": 54.5
    },
    {
      "Name": "Farnica",
      "ID": 1431,
			"CoordX": 345.6,
      "CoordY": 53.6
    },
    {
      "Name": "Sivoria",
      "ID": 1432,
			"CoordX": 345.6,
      "CoordY": 52.7
    },
    {
      "Name": "Talcharaim",
      "ID": 1433,
			"CoordX": 345.8,
      "CoordY": 51.7
    }
  ]
}